cheltuieli/__init__.py
cheltuieli/chelt_plan.py
cheltuieli/chelt_real.py
cheltuieli/control.py
cheltuieli/kalendar.py
cheltuieli/masina.py
cheltuieli/plan_vs_real.py
cheltuieli/GUI/2del_check_expiration.ui
cheltuieli/GUI/chelt_plan.ui
cheltuieli/GUI/chelt_real.ui
cheltuieli/GUI/filterWindow.ui
cheltuieli/GUI/plan_vs_real.ui
cheltuieli/SQL/cheltuieli_desktop.sql
cheltuieli/static/taxes.csv
cheltuieli-0.2.1.dist-info/METADATA
cheltuieli-0.2.1.dist-info/WHEEL
cheltuieli-0.2.1.dist-info/top_level.txt
cheltuieli-0.2.1.dist-info/RECORD
